grouponefunctions/__init__.py
grouponefunctions/grouponefunctions.py
grouponefunctions-0.1.8.dist-info/LICENSE
grouponefunctions-0.1.8.dist-info/WHEEL
grouponefunctions-0.1.8.dist-info/METADATA
grouponefunctions-0.1.8.dist-info/RECORD
