Metadata-Version: 2.1
Name: grouponefunctions
Version: 0.1.8
Summary: A package containing the necessary functions to smoothly run the analysis in DSCI-310-Group-1
License: MIT
Author: Andres Perez, Daniel Hou, Zizhen Guo, Timothy Zhou
Requires-Python: >=3.9,<3.11
Classifier: License :: OSI Approved :: MIT License
Classifier: Programming Language :: Python :: 3
Classifier: Programming Language :: Python :: 3.10
Classifier: Programming Language :: Python :: 3.9
Requires-Dist: matplotlib (>=3.5.1)
Requires-Dist: numpy (==1.21.5)
Requires-Dist: pandas (>=1.4.2)
